README
setup.py
Nikweb.egg-info/PKG-INFO
Nikweb.egg-info/SOURCES.txt
Nikweb.egg-info/dependency_links.txt
Nikweb.egg-info/top_level.txt
nikweb/__init__.py
nikweb/render.py
nikweb/http/__init__.py
nikweb/http/django_views.py
nikweb/http/webob_server.py