Metadata-Version: 1.1
Name: Nikweb
Version: 0.1.0
Summary: A GeoJSON web service for Mapnik
Home-page: http://code.google.com/p/mapnik-utils/
Author: Robert Coup
Author-email: robert@coup.net.nz
License: UNKNOWN
Keywords: mapnik,gis,geospatial,webob,django
Platform: UNKNOWN
Classifier: Development Status :: 4 - Beta
Classifier: Environment :: Web Environment
Classifier: Framework :: Django
Classifier: License :: OSI Approved :: GNU Library or Lesser General Public License (LGPL)
Classifier: Intended Audience :: Developers
Classifier: Intended Audience :: Science/Research
Classifier: Operating System :: OS Independent
Classifier: Programming Language :: Python
Classifier: Topic :: Scientific/Engineering :: GIS
Classifier: Topic :: Internet :: WWW/HTTP :: Dynamic Content
Classifier: Topic :: Utilities
Requires: mapnik (>=0.6.0)
Provides: nikweb
